dockai/__init__.py
dockai/agents/__init__.py
dockai/agents/agent_functions.py
dockai/agents/analyzer.py
dockai/agents/generator.py
dockai/agents/reviewer.py
dockai/cli/__init__.py
dockai/cli/main.py
dockai/cli/ui.py
dockai/core/__init__.py
dockai/core/agent_context.py
dockai/core/errors.py
dockai/core/llm_providers.py
dockai/core/mcp_server.py
dockai/core/schemas.py
dockai/core/state.py
dockai/utils/__init__.py
dockai/utils/callbacks.py
dockai/utils/code_intelligence.py
dockai/utils/context_retriever.py
dockai/utils/file_utils.py
dockai/utils/indexer.py
dockai/utils/language_configs.py
dockai/utils/metrics.py
dockai/utils/ollama_docker.py
dockai/utils/prompts.py
dockai/utils/rate_limiter.py
dockai/utils/registry.py
dockai/utils/scanner.py
dockai/utils/tracing.py
dockai/utils/validator.py
dockai/workflow/__init__.py
dockai/workflow/graph.py
dockai/workflow/nodes.py
dockai_cli-4.0.7.dist-info/licenses/LICENSE
dockai_cli-4.0.7.dist-info/METADATA
dockai_cli-4.0.7.dist-info/WHEEL
dockai_cli-4.0.7.dist-info/entry_points.txt
dockai_cli-4.0.7.dist-info/top_level.txt
dockai_cli-4.0.7.dist-info/RECORD
