Metadata-Version: 2.4
Name: dockai-cli
Version: 4.0.7
Summary: The Customizable AI Dockerfile Generation Framework
Author-email: Januda Bethmin <desilvabethmin@gmail.com>
Classifier: Programming Language :: Python :: 3
Classifier: License :: OSI Approved :: MIT License
Classifier: Operating System :: OS Independent
Requires-Python: >=3.10
License-File: LICENSE
Requires-Dist: openai>=2.0.0
Requires-Dist: httpx>=0.27.0
Requires-Dist: typer>=0.12.0
Requires-Dist: rich>=13.7.0
Requires-Dist: python-dotenv>=1.0.0
Requires-Dist: pathspec>=0.11.0
Requires-Dist: langgraph>=0.2.0
Requires-Dist: langchain-core>=0.3.0
Requires-Dist: langchain-openai>=0.2.0
Requires-Dist: langchain-google-genai>=2.0.0
Requires-Dist: langchain-anthropic>=0.3.0
Requires-Dist: mcp>=1.0.0
Requires-Dist: langchain-ollama>=0.2.0
Requires-Dist: opentelemetry-api>=1.20.0
Requires-Dist: opentelemetry-sdk>=1.20.0
Requires-Dist: opentelemetry-exporter-otlp>=1.20.0
Requires-Dist: langsmith>=0.1.0
Requires-Dist: sentence-transformers>=2.2.0
Requires-Dist: numpy>=1.24.0
Provides-Extra: test
Requires-Dist: pytest>=7.4.0; extra == "test"
Requires-Dist: pytest-cov>=4.1.0; extra == "test"
Requires-Dist: pytest-mock>=3.12.0; extra == "test"
Provides-Extra: all
Requires-Dist: dockai-cli[test]; extra == "all"
Dynamic: license-file
